tubecutterdxf/__init__.py
tubecutterdxf/tubecutterdxf.py
tubecutterdxf-0.1.4.dist-info/METADATA
tubecutterdxf-0.1.4.dist-info/WHEEL
tubecutterdxf-0.1.4.dist-info/licenses/LICENSE.md
tubecutterdxf-0.1.4.dist-info/licenses/LICENSE_EE.md
tubecutterdxf-0.1.4.dist-info/RECORD
