Metadata-Version: 2.4
Name: tubecutterdxf
Version: 0.1.4
Summary: Programmatically create Spiral and Brickwork patterns for laser cutting tubing
Project-URL: Homepage, https://github.com/qwiebe/TubeCutterDXF
Project-URL: Issues, https://github.com/qwiebe/TubeCutterDXF/issues
Author: qwiebe
License-Expression: LicenseRef-Sustainable-Use-License-v1.0
License-File: LICENSE.md
License-File: LICENSE_EE.md
Keywords: CAD,DXF,Patterns
Classifier: License :: Other/Proprietary License
Classifier: Operating System :: OS Independent
Classifier: Programming Language :: Python :: 3
Requires-Python: >=3.12.4
Requires-Dist: ezdxf==1.3.5
Requires-Dist: matplotlib==3.10.0
Requires-Dist: numpy==2.2.2
Requires-Dist: prettytable==3.14.0
